[
    {
        "id": 1,
        "nome": "Onix LT 1.0",
        "marca": "Chevrolet",
        "ano": 2022,
        "cor": "Preto",
        "quilometragem": 15000,
        "preco_diaria": 100.00,
        "descricao": "Carro compacto econômico, ideal para cidade",
        "imagem": "../assets/onix.jpg",
        "disponivel": true
    },
    {
        "id": 2,
        "nome": "HB20 Vision",
        "marca": "Hyundai",
        "ano": 2023,
        "cor": "Silver",
        "quilometragem": 25000,
        "preco_diaria": 120.00,
        "descricao": "Carro compacto com ótimo custo-benefício",
        "imagem": "../assets/hb20.jpg",
        "disponivel": true
    },
    {
        "id": 3,
        "nome": "Renegade Longitude",
        "marca": "Jeep",
        "ano": 2023,
        "cor": "Branco",
        "quilometragem": 18000,
        "preco_diaria": 180.00,
        "descricao": "SUV compacto com ótimo desempenho",
        "imagem": "../assets/renegade.jpg",
        "disponivel": true
    },
    {
        "id": 4,
        "nome": "Corolla XEI 2.0",
        "marca": "Toyota",
        "ano": 2021,
        "cor": "Prata",
        "quilometragem": 30000,
        "preco_diaria": 150.00,
        "descricao": "Sedan médio com conforto e economia",
        "imagem": "../assets/corolla.jpg",
        "disponivel": true
    },
    {
        "id": 5,
        "nome": "Compass Limited",
        "marca": "Jeep",
        "ano": 2022,
        "cor": "Vermelho",
        "quilometragem": 22000,
        "preco_diaria": 200.00,
        "descricao": "SUV médio com tecnologia e conforto",
        "imagem": "../assets/compass.jpg",
        "disponivel": true
    },
    {
        "id": 6,
        "nome": "Civic Touring",
        "marca": "Honda",
        "ano": 2023,
        "cor": "Azul",
        "quilometragem": 12000,
        "preco_diaria": 170.00,
        "descricao": "Sedan esportivo com tecnologia avançada",
        "imagem": "../assets/civic.jpg",
        "disponivel": true
    }
]
